pinkeys/__init__.py
pinkeys/__main__.py
pinkeys-0.1.5.dist-info/DESCRIPTION.rst
pinkeys-0.1.5.dist-info/METADATA
pinkeys-0.1.5.dist-info/RECORD
pinkeys-0.1.5.dist-info/WHEEL
pinkeys-0.1.5.dist-info/entry_points.txt
pinkeys-0.1.5.dist-info/metadata.json
pinkeys-0.1.5.dist-info/top_level.txt
