Metadata-Version: 2.0
Name: pinkeys
Version: 0.1.5
Summary: PINKEYS privacy keys directory tool. It provide quick access to public keys like (e.g., ssh, pgp and others).
Home-page: https://github.com/pinkeys/pinkeys-cli
Author: PINKEYS CORP.
Author-email: support@pinkeys.com
License: UNKNOWN
Keywords: ssh pgp security keys
Platform: UNKNOWN
Classifier: Development Status :: 3 - Alpha
Classifier: Intended Audience :: Developers
Classifier: Topic :: Software Development :: Build Tools
Classifier: License :: OSI Approved :: MIT License
Classifier: Programming Language :: Python :: 3
Classifier: Programming Language :: Python :: 3.4
Classifier: Programming Language :: Python :: 3.5
Classifier: Programming Language :: Python :: 3.6
Requires-Dist: begins
Requires-Dist: requests
Requires-Dist: argparse
Requires-Dist: funcsigs
